{
  "chisel_use": {
    "subtitle": "sounds.eggsandgrits.chisel_use",
    "sounds": [
      "eggsandgrits:chisel_use"
    ]
  },
  "magic_block_break": {
    "subtitle": "sounds.eggsandgrits.magic_block_break",
    "sounds": [
      "eggsandgrits:magic_block_break"
    ]
  },
  "magic_block_step": {
    "subtitle": "sounds.eggsandgrits.magic_block_step",
    "sounds": [
      "eggsandgrits:magic_block_step"
    ]
  },
  "magic_block_place": {
    "subtitle": "sounds.eggsandgrits.toot",
    "sounds": [
      "eggsandgrits:toot"
    ]
  },
  "magic_block_hit": {
    "subtitle": "sounds.eggsandgrits.magic_block_hit",
    "sounds": [
      "eggsandgrits:magic_block_hit"
    ]
  },
  "magic_block_fall": {
    "subtitle": "sounds.eggsandgrits.magic_block_fall",
    "sounds": [
      "eggsandgrits:magic_block_fall"
    ]
  },
  "bar_brawl": {
    "sounds": [
      {
        "name": "eggsandgrits:bar_brawl",
        "stream": true
      }
    ]
  },
  "toot": {
    "subtitle": "toot",
    "sounds": [
      "eggsandgrits:toot"
    ]
  },
  "toot2": {
    "subtitle": "toot2",
    "sounds": [
      "eggsandgrits:toot2"
    ]
  },
  "cough": {
    "subtitle": "cough",
    "sounds": [
      "eggsandgrits:cough"
    ]
  },
  "cough2": {
    "subtitle": "cough2",
    "sounds": [
      "eggsandgrits:cough2"
    ]
  },
  "do_not_eat": {
    "subtitle": "Larry",
    "sounds": [
      "eggsandgrits:do_not_eat"
    ]
  },
  "he_did_what": {
    "subtitle": "Larry",
    "sounds": [
      "eggsandgrits:he_did_what"
    ]
  },
  "git_r_done": {
    "subtitle": "Larry",
    "sounds": [
      "eggsandgrits:git_r_done"
    ]
  }
}